Metadata-Version: 1.2
Name: sequana-sphinxext
Version: 1.0.0
Summary: A set of sphinx extension for Sequana pipelines, wrappers and rules
Home-page: http://github.com/sequana/sequana_sphinxext
Author: Thomas Cokelaer
Author-email: thomas.cokelaer@pasteur.fr
Maintainer: Thomas Cokelaer
Maintainer-email: thomas.cokelaer@pasteur.fr
License: new BSD
Keywords: NGS,snakemake
Platform: Linux
Platform: Unix
Platform: MacOsX
Platform: Windows
Classifier: Development Status :: 5 - Production/Stable
Classifier: Intended Audience :: Developers
Classifier: Intended Audience :: Science/Research
Classifier: License :: OSI Approved :: BSD License
Classifier: Operating System :: OS Independent
Classifier: Programming Language :: Python :: 3.7
Classifier: Programming Language :: Python :: 3.8
Classifier: Programming Language :: Python :: 3.9
Classifier: Topic :: Software Development :: Libraries :: Python Modules
Classifier: Topic :: Scientific/Engineering :: Bio-Informatics
Classifier: Topic :: Scientific/Engineering :: Information Analysis
Classifier: Topic :: Scientific/Engineering :: Mathematics
Classifier: Topic :: Scientific/Engineering :: Physics
